{
    "calendarYear": 1492,
    "dayInMonth": [
        31,
        30,
        30,
        31,
        30,
        30,
        31,
        30,
        31,
        30,
        31,
        30
    ],
    "dayInWeek": 10,
    "dayNames": [
        "Oneday",
        "Twoday",
        "Threeday",
        "Fourday",
        "Fiveday",
        "Sixday",
        "Sevenday",
        "Eightday",
        "Nineday",
        "Tenday"
    ],
    "hourPerDay": 24,
    "lastYearStartDay": 0,
    "leapYearDays": 1,
    "leapYearFormula": "year % 4 == 0",
    "leapYearMonth": 6,
    "minutePerHour": 60,
    "months": [
        "Hammer",
        "Alturiak",
        "Ches",
        "Tarsakh",
        "Mirtul",
        "Kythorn",
        "Flamerule",
        "Eleasias",
        "Eleint",
        "Marpenoth",
        "Uktar",
        "Nightal"
    ],
    "mostWeekInMonth": 4,
    "nextYearStartDay": 2,
    "seasons": [
        "Early Summer",
        "Late Summer",
        "Early Autumn",
        "Late Autumn",
        "Early Winter",
        "Late Winter",
        "Early Spring",
        "Late Spring"
    ],
    "seasonDistribution":[
        ["Early Winter", "Late Winter"],
        ["Late Winter"],
        ["Early Spring"],
        ["Late Spring", "Early Spring"],
        ["Late Spring"],
        ["Early Summer"],
        ["Early Summer", "Late Summer"],
        ["Late Summer"],
        ["Early Autumn"],
        ["Early Autumn","Late Autumn"],
        ["Late Autumn"],
        ["Early Winter"]
    ],
    "secondPerMinute": 60,
    "yearStartDay": 1
}